Metadata-Version: 2.1
Name: zip-deploy
Version: 0.1.5
Summary: Provides an easy way to fetch contents from a remote ZIP files and sync/extract them to a local destination dir.
Home-page: https://github.com/hgross/zip-deploy
Author: Henning Gross
Author-email: mail.to@henning-gross.de
License: MIT
Keywords: zip,deploy,cache
Platform: UNKNOWN
Requires-Python: >=3.6
